README.md
setup.py
augmentatio/__init__.py
augmentatio.egg-info/PKG-INFO
augmentatio.egg-info/SOURCES.txt
augmentatio.egg-info/dependency_links.txt
augmentatio.egg-info/not-zip-safe
augmentatio.egg-info/requires.txt
augmentatio.egg-info/top_level.txt
requests/__version__.py