Metadata-Version: 2.4
Name: augmentatio
Version: 0.0.1
Summary: A profoundly meaningless Python package that does absolutely augmentatio.
Home-page: https://example.com/augmentatio
Author: Anonymous augmentatio Engineer
Author-email: vasjakorolevcd4413@autorambler.ru
Keywords: augmentatio nonsense placeholder meaningless verbose
Classifier: Development Status :: 1 - Planning
Classifier: License :: OSI Approved :: MIT License
Classifier: Programming Language :: Python :: 3
Classifier: Programming Language :: Python :: 3 :: Only
Classifier: Topic :: Software Development :: Libraries
Classifier: Topic :: Utilities
Requires-Python: >=3.7
Requires-Dist: requests
Dynamic: author
Dynamic: author-email
Dynamic: classifier
Dynamic: description
Dynamic: description-content-type
Dynamic: home-page
Dynamic: keywords
Dynamic: requires-dist
Dynamic: requires-python
Dynamic: summary
